[
  {
    "name": "ZS-1/24",
    "contractor": "K1"
  },
  {
    "name": "ZS-2/24",
    "contractor": "K1"
  },
  {
    "name": "ZS-3/24",
    "contractor": "K1"
  },
  {
    "name": "ZS-4/24",
    "contractor": "K1"
  },
  {
    "name": "ZS-5/24",
    "contractor": "K1"
  },
  {
    "name": "ZS-6/24",
    "contractor": "K1"
  },
  {
    "name": "ZS-7/24",
    "contractor": "K1"
  },
  {
    "name": "ZS-8/24",
    "contractor": "K1"
  },
  {
    "name": "ZS-9/24",
    "contractor": "K1"
  },
  {
    "name": "ZS-10/24",
    "contractor": "K1"
  },
  {
    "name": "ZS-11/24",
    "contractor": "K1"
  },
  {
    "name": "ZS-12/24",
    "contractor": "K1"
  },
  {
    "name": "ZS-13/24",
    "contractor": "K1"
  }
]